Metadata-Version: 2.1
Name: ssdb-manager
Version: 0.2.0.post1
Summary: Facilitates interaction between Python and SQL Server Management Studio
Home-page: https://github.com/tsdatateam/ssdb_manager
Author: Tishman Speyer Data Analytics
Author-email: ts.datateam@gmail.com
License: MIT
Keywords: SQL,Server,pandas,Python,SSMS,Query,Database
Classifier: Development Status :: 3 - Alpha
Classifier: License :: OSI Approved :: MIT License
Classifier: Programming Language :: Python :: 3
Classifier: Programming Language :: Python :: 3.5
Classifier: Programming Language :: Python :: 3.6
Classifier: Programming Language :: Python :: 3.7
Classifier: Programming Language :: Python :: 3.8
Classifier: Programming Language :: Python :: 3.9
Classifier: Programming Language :: Python :: 3.10
